azureml/dataprep/rslex.cpython-39-x86_64-linux-gnu.so
azureml/dataprep/rslex_fuse_subprocess_wrapper/__init__.py
azureml_dataprep_rslex.libs/libfuse-244bbfcb.so.2.9.2
azureml_dataprep_rslex.libs/libkrb5support-d0bcff84.so.0.1
azureml_dataprep_rslex.libs/libkeyutils-dfe70bd6.so.1.5
azureml_dataprep_rslex.libs/libgssapi_krb5-497db0c6.so.2.2
azureml_dataprep_rslex.libs/libcrypto-d3570994.so.1.0.2k
azureml_dataprep_rslex.libs/libkrb5-fcafa220.so.3.3
azureml_dataprep_rslex.libs/libcom_err-2abe824b.so.2.1
azureml_dataprep_rslex.libs/libk5crypto-b1f99d5c.so.3.1
azureml_dataprep_rslex.libs/libselinux-0922c95c.so.1
azureml_dataprep_rslex.libs/libssl-cd1d6220.so.1.0.2k
azureml_dataprep_rslex.libs/libpcre-9513aab5.so.1.2.0
azureml_dataprep_rslex-2.25.1.dist-info/top_level.txt
azureml_dataprep_rslex-2.25.1.dist-info/WHEEL
azureml_dataprep_rslex-2.25.1.dist-info/METADATA
azureml_dataprep_rslex-2.25.1.dist-info/RECORD
azureml_dataprep_rslex-2.25.1.dist-info/licenses/LICENSE.txt
azureml_dataprep_rslex-2.25.1.dist-info/licenses/NOTICE.txt
