Metadata-Version: 2.1
Name: azureml-dataprep-rslex
Version: 2.25.1
Summary: Azure ML Data Preparation RustLex
Home-page: http://aka.ms/data-prep-sdk
Author: Microsoft Corporation
Author-email: dataprepms@microsoft.com
Classifier: Development Status :: 5 - Production/Stable
Classifier: Intended Audience :: Developers
Classifier: Intended Audience :: Science/Research
Classifier: License :: Other/Proprietary License
Classifier: Programming Language :: Python
Classifier: Programming Language :: Python :: 3 :: Only
Classifier: Programming Language :: Python :: 3.7
Classifier: Programming Language :: Python :: 3.8
Classifier: Programming Language :: Python :: 3.9
Classifier: Programming Language :: Python :: 3.10
Classifier: Programming Language :: Python :: 3.11
Classifier: Operating System :: MacOS
Classifier: Operating System :: Microsoft :: Windows
Classifier: Operating System :: POSIX :: Linux
Classifier: Topic :: Scientific/Engineering
License-File: LICENSE.txt
License-File: NOTICE.txt
